CHANGES.rst
CONTRIBUTORS.rst
MANIFEST.in
README.rst
setup.cfg
setup.py
docs/LICENSE.GPL
docs/LICENSE.rst
docs/index.rst
src/collective/__init__.py
src/collective.autoscaling.egg-info/PKG-INFO
src/collective.autoscaling.egg-info/SOURCES.txt
src/collective.autoscaling.egg-info/dependency_links.txt
src/collective.autoscaling.egg-info/entry_points.txt
src/collective.autoscaling.egg-info/namespace_packages.txt
src/collective.autoscaling.egg-info/not-zip-safe
src/collective.autoscaling.egg-info/requires.txt
src/collective.autoscaling.egg-info/top_level.txt
src/collective/autoscaling/__init__.py
src/collective/autoscaling/configure.zcml
src/collective/autoscaling/interfaces.py
src/collective/autoscaling/resizing.py
src/collective/autoscaling/setuphandlers.py
src/collective/autoscaling/subscribers.py
src/collective/autoscaling/testing.py
src/collective/autoscaling/testing.zcml
src/collective/autoscaling/upgrades.py
src/collective/autoscaling/upgrades.zcml
src/collective/autoscaling/utils.py
src/collective/autoscaling/browser/__init__.py
src/collective/autoscaling/browser/autoscaling.png
src/collective/autoscaling/browser/configure.zcml
src/collective/autoscaling/browser/controlpanel.py
src/collective/autoscaling/browser/resizing.py
src/collective/autoscaling/locales/collective.autoscaling.pot
src/collective/autoscaling/locales/update.sh
src/collective/autoscaling/locales/en/LC_MESSAGES/collective.autoscaling.po
src/collective/autoscaling/locales/fr/LC_MESSAGES/collective.autoscaling.po
src/collective/autoscaling/locales/no/LC_MESSAGES/collective.autoscaling.po
src/collective/autoscaling/locales/pt/LC_MESSAGES/collective.autoscaling.po
src/collective/autoscaling/profiles/default/browserlayer.xml
src/collective/autoscaling/profiles/default/collectiveautoscaling_default.txt
src/collective/autoscaling/profiles/default/controlpanel.xml
src/collective/autoscaling/profiles/default/metadata.xml
src/collective/autoscaling/profiles/default/registry.xml
src/collective/autoscaling/profiles/testing/metadata.xml
src/collective/autoscaling/profiles/testing/types.xml
src/collective/autoscaling/profiles/testing/types/dexterity_content_type_with_two_image_fields.xml
src/collective/autoscaling/profiles/uninstall/browserlayer.xml
src/collective/autoscaling/profiles/uninstall/controlpanel.xml
src/collective/autoscaling/profiles/uninstall/registry.xml
src/collective/autoscaling/tests/__init__.py
